{
  "updatedAt": "2026-03-16T02:04:11.320Z",
  "source": "Wikipedia, Al Jazeera, HRANA, Reuters",
  "casualties": {
    "iran": {
      "killed": 3065,
      "wounded": 18551
    },
    "lebanon": {
      "killed": 850,
      "wounded": 2105
    },
    "iraq": {
      "killed": 65,
      "wounded": 93
    },
    "israel": {
      "killed": 19,
      "wounded": 3195
    },
    "usa": {
      "killed": 15,
      "wounded": 200
    },
    "kuwait": {
      "killed": 8,
      "wounded": 99
    },
    "uae": {
      "killed": 6,
      "wounded": 141
    },
    "oman": {
      "killed": 3,
      "wounded": 5
    },
    "bahrain": {
      "killed": 2,
      "wounded": 38
    },
    "saudi": {
      "killed": 2,
      "wounded": 12
    },
    "jordan": {
      "killed": 0,
      "wounded": 19
    },
    "qatar": {
      "killed": 0,
      "wounded": 16
    },
    "yemen": {
      "killed": 0,
      "wounded": 0
    },
    "syria": {
      "killed": 0,
      "wounded": 0
    },
    "palestine": {
      "killed": 0,
      "wounded": 0
    }
  }
}
